dmario24_cli/__init__.py
dmario24_cli/cli.py
dmario24_cli/utils.py
dmario24_cli-0.1.0.dist-info/METADATA
dmario24_cli-0.1.0.dist-info/WHEEL
dmario24_cli-0.1.0.dist-info/entry_points.txt
dmario24_cli-0.1.0.dist-info/top_level.txt
dmario24_cli-0.1.0.dist-info/RECORD
